cochl/__init__.py
cochl/sense/__init__.py
cochl/sense/config.py
cochl/sense/exceptions.py
cochl/sense/file.py
cochl/sense/requirements.txt
cochl/sense/result.py
cochl/sense/stream.py
cochl/sense/version.py
ccsy-0.0.1.dist-info/METADATA
ccsy-0.0.1.dist-info/WHEEL
ccsy-0.0.1.dist-info/licenses/LICENSE
ccsy-0.0.1.dist-info/RECORD
