Metadata-Version: 2.3
Name: ccsy
Version: 0.0.1
Summary: Cochl Sense
Project-URL: Homepage, https://github.com/cochlearai/cochl-sense-py
Project-URL: Issues, https://github.com/cochlearai/cochl-sense-py/issues
Author-email: Seungmin Yoon <smyoon@cochl.ai>
License-File: LICENSE
Classifier: License :: OSI Approved :: MIT License
Classifier: Operating System :: OS Independent
Classifier: Programming Language :: Python :: 3
Requires-Python: >=3.8
Requires-Dist: cochl-sense-api==1.6.0
Requires-Dist: pyaudio
Requires-Dist: requests
Requires-Dist: soundfile
